llama_index/embeddings/cloudflare_workersai/__init__.py
llama_index/embeddings/cloudflare_workersai/base.py
llama_index_embeddings_cloudflare_workersai-0.4.1.dist-info/METADATA
llama_index_embeddings_cloudflare_workersai-0.4.1.dist-info/WHEEL
llama_index_embeddings_cloudflare_workersai-0.4.1.dist-info/licenses/LICENSE
llama_index_embeddings_cloudflare_workersai-0.4.1.dist-info/RECORD
